zdppy_redis/__init__.py
zdppy_redis/async_redis.py
zdppy_redis/zdppy_redis.py
zdppy_redis-0.1.0.dist-info/LICENSE
zdppy_redis-0.1.0.dist-info/WHEEL
zdppy_redis-0.1.0.dist-info/METADATA
zdppy_redis-0.1.0.dist-info/RECORD
